collageradiomics.py
collageradiomics_core-0.1.2.1.dist-info/LICENSE
collageradiomics_core-0.1.2.1.dist-info/METADATA
collageradiomics_core-0.1.2.1.dist-info/WHEEL
collageradiomics_core-0.1.2.1.dist-info/top_level.txt
collageradiomics_core-0.1.2.1.dist-info/RECORD
