Metadata-Version: 2.1
Name: collageradiomics-core
Version: 0.1.2.1
Summary: CoLliage Implementation
Home-page: https://github.com/ccipd/collageradiomics
Author: BriC Lab
Author-email: toth-tech@hillyer.me
License: UNKNOWN
Keywords: radiomics cancerimaging medicalresearch computationalimaging
Platform: UNKNOWN
Classifier: Development Status :: 3 - Alpha
Classifier: Intended Audience :: Science/Research
Classifier: Intended Audience :: Developers
Classifier: License :: OSI Approved :: BSD License
Classifier: Operating System :: OS Independent
Classifier: Operating System :: POSIX :: Linux
Classifier: Operating System :: Microsoft :: Windows :: Windows 10
Classifier: Operating System :: MacOS
Classifier: Programming Language :: Python :: 3
Classifier: Topic :: Scientific/Engineering :: Bio-Informatics
Requires-Python: >=3.6
Requires-Dist: numpy (==1.19.0)
Requires-Dist: scikit-learn (==0.23.1)
Requires-Dist: scikit-build (==0.11.1)
Requires-Dist: scikit-image (==0.17.2)
Requires-Dist: mahotas (==1.4.10)
Requires-Dist: scipy (==1.5.0)
